larigira/__init__.py
larigira/audioform_base.py
larigira/audioform_http.py
larigira/audioform_mostrecent.py
larigira/audioform_podcast.py
larigira/audioform_randomdir.py
larigira/audioform_script.py
larigira/audioform_static.py
larigira/audiogen.py
larigira/audiogen_http.py
larigira/audiogen_mostrecent.py
larigira/audiogen_mpdrandom.py
larigira/audiogen_podcast.py
larigira/audiogen_randomdir.py
larigira/audiogen_script.py
larigira/audiogen_static.py
larigira/config.py
larigira/db.py
larigira/entrypoints_utils.py
larigira/event.py
larigira/event_manage.py
larigira/eventutils.py
larigira/forms.py
larigira/formutils.py
larigira/fsutils.py
larigira/main.py
larigira/mpc.py
larigira/rpc.py
larigira/test_unused.py
larigira/timeform_base.py
larigira/timeform_cron.py
larigira/timegen.py
larigira/timegen_cron.py
larigira/timegen_every.py
larigira/timegen_exclusions.py
larigira/unused.py
larigira/dbadmin/__init__.py
larigira/dbadmin/suggestions.py
larigira/dbadmin/templates/add_audio.html
larigira/dbadmin/templates/add_audio_kind.html
larigira/dbadmin/templates/add_time.html
larigira/dbadmin/templates/add_time_kind.html
larigira/dbadmin/templates/calendar.html
larigira/dbadmin/templates/dbadmin_base.html
larigira/dbadmin/templates/edit_event.html
larigira/dbadmin/templates/list.html
larigira/filters/__init__.py
larigira/filters/basic.py
larigira/filters/tests/test_basic.py
larigira/static/calendar.js
larigira/static/datetime.js
larigira/static/jqueryui/LICENSE.txt
larigira/static/jqueryui/jquery-ui.css
larigira/static/jqueryui/jquery-ui.js
larigira/static/jqueryui/jquery-ui.min.css
larigira/static/jqueryui/jquery-ui.min.js
larigira/static/jqueryui/jquery-ui.theme.css
larigira/static/jqueryui/jquery-ui.theme.min.css
larigira/static/jqueryui/images/ui-icons_444444_256x240.png
larigira/static/jqueryui/images/ui-icons_555555_256x240.png
larigira/static/jqueryui/images/ui-icons_777620_256x240.png
larigira/static/jqueryui/images/ui-icons_777777_256x240.png
larigira-1.4.1.dist-info/METADATA
larigira-1.4.1.dist-info/WHEEL
larigira-1.4.1.dist-info/entry_points.txt
larigira-1.4.1.dist-info/top_level.txt
larigira-1.4.1.dist-info/RECORD
