Metadata-Version: 2.2
Name: larigira
Version: 1.4.1
Summary: A radio automation based on MPD
Author-email: boyska <piuttosto@logorroici.org>
License: AGPL-3.0-only
Project-URL: Homepage, https://git.lattuga.net/boyska/larigira
Project-URL: Documentation, https://boyska.degenerazione.xyz/larigira/doc/
Project-URL: Repository, https://git.lattuga.net/boyska/larigira
Project-URL: Issues, https://git.lattuga.net/boyska/larigira/issues
Project-URL: Changelog, https://git.lattuga.net/boyska/larigira/src/branch/master/doc/source/changelog.md
Keywords: radio automation,music
Classifier: License :: OSI Approved :: GNU Affero General Public License v3
Classifier: Topic :: Multimedia :: Sound/Audio
Requires-Python: >=3.8
Requires-Dist: Babel==2.17.0
Requires-Dist: Flask-Babel==4.0.*
Requires-Dist: Flask-WTF==1.2.*
Requires-Dist: Jinja2==3.1.4
Requires-Dist: cachelib==0.1
Requires-Dist: croniter==3.0.*
Requires-Dist: flask-bootstrap==3.3.*
Requires-Dist: flask==3.1.0; python_version >= "3.9"
Requires-Dist: flask==3.0.*; python_version < "3.9"
Requires-Dist: gevent==24.11.1; python_version >= "3.9"
Requires-Dist: gevent==23.9.*; python_version < "3.9"
Requires-Dist: itsdangerous==2.2.0
Requires-Dist: lxml==5.3.1
Requires-Dist: python-mpd2
Requires-Dist: pytimeparse==1.1.8
Requires-Dist: pyxdg==0.26
Requires-Dist: requests==2.*
Requires-Dist: tinydb==3.12.2
Requires-Dist: urllib3==1.*
Requires-Dist: werkzeug==3.1.3; python_version >= "3.9"
Requires-Dist: werkzeug==3.0.*; python_version < "3.9"
Requires-Dist: wtforms==2.2.1
Provides-Extra: percentwait
Requires-Dist: mutagen==1.47.*; extra == "percentwait"
Provides-Extra: dev
Requires-Dist: pytest; extra == "dev"
Provides-Extra: all
Requires-Dist: larigira[dev,percentwait]; extra == "all"
Provides-Extra: docs
Requires-Dist: markdown-it-py==3.0.0; extra == "docs"
Requires-Dist: MarkupSafe==3.0.2; extra == "docs"
Requires-Dist: myst-parser==4.0.1; extra == "docs"
Requires-Dist: sphinx-multiversion==0.2.4; extra == "docs"
Requires-Dist: Sphinx==8.2.1; extra == "docs"
Requires-Dist: sphinxcontrib-applehelp==2.0.0; extra == "docs"
Requires-Dist: sphinxcontrib-devhelp==2.0.0; extra == "docs"
Requires-Dist: sphinxcontrib-htmlhelp==2.1.0; extra == "docs"
Requires-Dist: sphinxcontrib-jsmath==1.0.1; extra == "docs"
Requires-Dist: sphinxcontrib-qthelp==2.0.0; extra == "docs"
Requires-Dist: sphinxcontrib-serializinghtml==2.0.0; extra == "docs"
Requires-Dist: toml==0.10.2; extra == "docs"
